<?xml version="1.0" encoding="utf-8"?>
<deployment>
  <id>3a0999a5784641df95c1289fd9d1a08c</id>
  <author>N/A</author>
  <deployer>OneDeploy</deployer>
  <authorEmail>N/A</authorEmail>
  <message>OneDeploy</message>
  <progress></progress>
  <status>Success</status>
  <statusText></statusText>
  <lastSuccessEndTime>2026-03-01T15:21:37.3165465Z</lastSuccessEndTime>
  <receivedTime>2026-03-01T15:21:35.7227484Z</receivedTime>
  <startTime>2026-03-01T15:21:35.7852402Z</startTime>
  <endTime>2026-03-01T15:21:37.3165465Z</endTime>
  <complete>True</complete>
  <is_temp>False</is_temp>
  <is_readonly>True</is_readonly>
  <project_type>OneDeploy</project_type>
  <vsproject_id></vsproject_id>
</deployment>